.gitignore
CHANGES.txt
LICENSE.rst
MANIFEST.in
Makefile
README.rst
setup.py
bin/cg
bin/clebg
carlfg.egg-info/PKG-INFO
carlfg.egg-info/SOURCES.txt
carlfg.egg-info/dependency_links.txt
carlfg.egg-info/not-zip-safe
carlfg.egg-info/requires.txt
carlfg.egg-info/top_level.txt
cg/ClebschGordan.py
cg/__init__.py
cg/german.py
docs/usage.rst