Metadata-Version: 1.0
Name: carlfg
Version: 0.31
Summary: find CG coefficients, find the sum of all natural numbers from 1 to n
Home-page: https://github.com/psachin/carlfg
Author: sachin
Author-email: isachin@iitb.ac.in
License: GNU GPLv3
